manage_simqsvr.py
simq/__init__.py
simq/admin.py
simq/apps.py
simq/models.py
simq/services.py
simq/settings.py
simq/tests.py
simq/urls.py
simq/views.py
simq/migrations/__init__.py
simqsvr/__init__.py
simqsvr/asgi.py
simqsvr/settings.py
simqsvr/urls.py
simqsvr/version.py
simqsvr/wsgi.py
simqsvr-0.1.3.dist-info/LICENSE
simqsvr-0.1.3.dist-info/METADATA
simqsvr-0.1.3.dist-info/WHEEL
simqsvr-0.1.3.dist-info/entry_points.txt
simqsvr-0.1.3.dist-info/top_level.txt
simqsvr-0.1.3.dist-info/RECORD
