Metadata-Version: 2.1
Name: simqsvr
Version: 0.1.3
Summary: SIMQ服务器。基于redis的消息队列，通过web接口提供对外服务。
Author: Chen Han
Maintainer: Chen Han
License: Apache License, Version 2.0
Keywords: django
Classifier: Development Status :: 5 - Production/Stable
Classifier: Intended Audience :: Developers
Classifier: Topic :: Software Development :: Libraries :: Python Modules
Classifier: License :: OSI Approved :: Apache Software License
Classifier: Programming Language :: Python :: 3
Classifier: Programming Language :: Python :: 3 :: Only
License-File: LICENSE
Requires-Dist: PyYAML
Requires-Dist: pydantic
Requires-Dist: requests
Requires-Dist: django
Requires-Dist: django-apis
Requires-Dist: django-redis
Requires-Dist: django-app-requires
Requires-Dist: django-environ-settings
